kraken_html/Class_kraken_html.py
kraken_html/Class_kraken_htmls.py
kraken_html/__init__.py
kraken_html/flask_routes.py
kraken_html/kraken_html.py
kraken_html/helpers/__init__.py
kraken_html/helpers/json.py
kraken_html/library/__init__.py
kraken_html/library/config/__init__.py
kraken_html/library/config/bootstrap_body.py
kraken_html/library/config/bootstrap_header.py
kraken_html/library/config/schema_record.py
kraken_html/library/form/__init__.py
kraken_html/library/form/form.py
kraken_html/library/html/__init__.py
kraken_html/library/html/accordion.py
kraken_html/library/html/anon.py
kraken_html/library/html/breadcrumb.py
kraken_html/library/html/button.py
kraken_html/library/html/card.py
kraken_html/library/html/cardgrid.py
kraken_html/library/html/carousel.py
kraken_html/library/html/citation.py
kraken_html/library/html/code.py
kraken_html/library/html/div.py
kraken_html/library/html/div_title.py
kraken_html/library/html/footer.py
kraken_html/library/html/form.py
kraken_html/library/html/form_input.py
kraken_html/library/html/html_nav.py
kraken_html/library/html/iframe.py
kraken_html/library/html/image.py
kraken_html/library/html/js_delayed_load.py
kraken_html/library/html/js_json_editor.py
kraken_html/library/html/link.py
kraken_html/library/html/list.py
kraken_html/library/html/map.py
kraken_html/library/html/media.py
kraken_html/library/html/modal.py
kraken_html/library/html/page.py
kraken_html/library/html/pagination.py
kraken_html/library/html/panes.py
kraken_html/library/html/paragraph.py
kraken_html/library/html/rating.py
kraken_html/library/html/schema_markup.py
kraken_html/library/html/section.py
kraken_html/library/html/summary.py
kraken_html/library/html/table.py
kraken_html/library/html/title.py
kraken_html/library/html/video.py
kraken_html/library/html/website.py
kraken_html/library/html_record/__init__.py
kraken_html/library/html_record/html_record.py
kraken_html/library/html_record/record_names.py
kraken_html/library/html_record/to_html.py
kraken_html-0.1.6.dist-info/LICENSE.txt
kraken_html-0.1.6.dist-info/METADATA
kraken_html-0.1.6.dist-info/WHEEL
kraken_html-0.1.6.dist-info/top_level.txt
kraken_html-0.1.6.dist-info/RECORD
