Metadata-Version: 2.1
Name: kraken-html
Version: 0.1.6
Summary: kraken-html
Home-page: https://github.com/tactik8/krakenhtml
Author: Tactik8
Author-email: info@tactik8.com
License: MIT
Classifier: License :: OSI Approved :: MIT License
Classifier: Programming Language :: Python :: 3
Classifier: Programming Language :: Python :: 3.10
License-File: LICENSE.txt
Requires-Dist: kraken-thing
Requires-Dist: requests
